{
	"info": {
		"_postman_id": "ca2138b4-ec41-4a55-b19e-4bd6d7000e89",
		"name": "W6-D3-BE",
		"schema": "https://schema.getpostman.com/json/collection/v2.1.0/collection.json",
		"_exporter_id": "24868828"
	},
	"item": [
		{
			"name": "edifici",
			"item": [
				{
					"name": "edifici",
					"request": {
						"method": "GET",
						"header": [],
						"url": {
							"raw": "http://localhost:8080/edifici",
							"protocol": "http",
							"host": [
								"localhost"
							],
							"port": "8080",
							"path": [
								"edifici"
							]
						}
					},
					"response": []
				},
				{
					"name": "edifici-byId",
					"request": {
						"method": "GET",
						"header": [],
						"url": {
							"raw": "http://localhost:8080/edifici/1",
							"protocol": "http",
							"host": [
								"localhost"
							],
							"port": "8080",
							"path": [
								"edifici",
								"1"
							]
						}
					},
					"response": []
				},
				{
					"name": "edifici_page",
					"protocolProfileBehavior": {
						"disableBodyPruning": true
					},
					"request": {
						"method": "GET",
						"header": [],
						"body": {
							"mode": "raw",
							"raw": "{\r\n    \"citta\": \"Roma\"\r\n}",
							"options": {
								"raw": {
									"language": "json"
								}
							}
						},
						"url": {
							"raw": "http://localhost:8080/edifici_page",
							"protocol": "http",
							"host": [
								"localhost"
							],
							"port": "8080",
							"path": [
								"edifici_page"
							]
						}
					},
					"response": []
				},
				{
					"name": "edifici-put",
					"request": {
						"method": "PUT",
						"header": [],
						"body": {
							"mode": "raw",
							"raw": "{\r\n    \"citta\": \"Bari\"\r\n}",
							"options": {
								"raw": {
									"language": "json"
								}
							}
						},
						"url": {
							"raw": "http://localhost:8080/edifici/1",
							"protocol": "http",
							"host": [
								"localhost"
							],
							"port": "8080",
							"path": [
								"edifici",
								"1"
							]
						}
					},
					"response": []
				},
				{
					"name": "edifici-post",
					"request": {
						"method": "POST",
						"header": [],
						"body": {
							"mode": "raw",
							"raw": "{\r\n    \"nome\": \"Palazzo Ciao\",\r\n    \"indirizzo\": \"Via Ciao, 10\",\r\n    \"citta\": \"Roma\",\r\n    \"postazioni\": null\r\n}",
							"options": {
								"raw": {
									"language": "json"
								}
							}
						},
						"url": {
							"raw": "http://localhost:8080/edifici",
							"protocol": "http",
							"host": [
								"localhost"
							],
							"port": "8080",
							"path": [
								"edifici"
							]
						}
					},
					"response": []
				},
				{
					"name": "edifici-del",
					"request": {
						"method": "DELETE",
						"header": [],
						"url": {
							"raw": "http://localhost:8080/edifici/2",
							"protocol": "http",
							"host": [
								"localhost"
							],
							"port": "8080",
							"path": [
								"edifici",
								"2"
							]
						}
					},
					"response": []
				}
			]
		},
		{
			"name": "Postazioni",
			"item": [
				{
					"name": "postazioniList",
					"request": {
						"method": "GET",
						"header": [],
						"url": {
							"raw": "http://localhost:8080/postazioni",
							"protocol": "http",
							"host": [
								"localhost"
							],
							"port": "8080",
							"path": [
								"postazioni"
							]
						}
					},
					"response": []
				},
				{
					"name": "postazioni-byId",
					"request": {
						"method": "GET",
						"header": [],
						"url": {
							"raw": "http://localhost:8080/postazioni/1",
							"protocol": "http",
							"host": [
								"localhost"
							],
							"port": "8080",
							"path": [
								"postazioni",
								"1"
							]
						}
					},
					"response": []
				},
				{
					"name": "postazioni_page",
					"request": {
						"method": "GET",
						"header": [],
						"url": {
							"raw": "http://localhost:8080/postazioni_page",
							"protocol": "http",
							"host": [
								"localhost"
							],
							"port": "8080",
							"path": [
								"postazioni_page"
							]
						}
					},
					"response": []
				},
				{
					"name": "postazioni-put",
					"request": {
						"method": "PUT",
						"header": [],
						"body": {
							"mode": "raw",
							"raw": "{\r\n    \"tipo\": \"PRIVATO\"\r\n}",
							"options": {
								"raw": {
									"language": "json"
								}
							}
						},
						"url": {
							"raw": "http://localhost:8080/postazioni/1",
							"protocol": "http",
							"host": [
								"localhost"
							],
							"port": "8080",
							"path": [
								"postazioni",
								"1"
							]
						}
					},
					"response": []
				},
				{
					"name": "postazioni-post",
					"request": {
						"method": "POST",
						"header": [],
						"body": {
							"mode": "raw",
							"raw": "{\r\n    \"nmaxOccupanti\": 5,\r\n    \"tipo\": \"OPENSPACE\"\r\n}",
							"options": {
								"raw": {
									"language": "json"
								}
							}
						},
						"url": {
							"raw": "http://localhost:8080/postazioni",
							"protocol": "http",
							"host": [
								"localhost"
							],
							"port": "8080",
							"path": [
								"postazioni"
							]
						}
					},
					"response": []
				},
				{
					"name": "postazioni-del",
					"request": {
						"method": "DELETE",
						"header": [],
						"url": {
							"raw": "http://localhost:8080/postazioni/3",
							"protocol": "http",
							"host": [
								"localhost"
							],
							"port": "8080",
							"path": [
								"postazioni",
								"3"
							]
						}
					},
					"response": []
				}
			]
		},
		{
			"name": "utenti",
			"item": [
				{
					"name": "utentiList",
					"request": {
						"method": "GET",
						"header": [],
						"url": {
							"raw": "http://localhost:8080/utenti",
							"protocol": "http",
							"host": [
								"localhost"
							],
							"port": "8080",
							"path": [
								"utenti"
							]
						}
					},
					"response": []
				},
				{
					"name": "utenti-byId",
					"request": {
						"method": "GET",
						"header": [],
						"url": {
							"raw": "http://localhost:8080/utenti/1",
							"protocol": "http",
							"host": [
								"localhost"
							],
							"port": "8080",
							"path": [
								"utenti",
								"1"
							]
						}
					},
					"response": []
				},
				{
					"name": "utenti_page",
					"request": {
						"method": "GET",
						"header": [],
						"url": {
							"raw": "http://localhost:8080/utenti_page",
							"protocol": "http",
							"host": [
								"localhost"
							],
							"port": "8080",
							"path": [
								"utenti_page"
							]
						}
					},
					"response": []
				},
				{
					"name": "utenti-put",
					"request": {
						"method": "PUT",
						"header": [],
						"body": {
							"mode": "raw",
							"raw": "{\r\n    \"nome\": \"Nicola\"\r\n}",
							"options": {
								"raw": {
									"language": "json"
								}
							}
						},
						"url": {
							"raw": "http://localhost:8080/utenti/2",
							"protocol": "http",
							"host": [
								"localhost"
							],
							"port": "8080",
							"path": [
								"utenti",
								"2"
							]
						}
					},
					"response": []
				},
				{
					"name": "utenti-post",
					"request": {
						"method": "POST",
						"header": [],
						"body": {
							"mode": "raw",
							"raw": "{\r\n    \"email\": \"marco@mail.com\",\r\n    \"nome\": \"Marco\",\r\n    \"username\": \"marcolizzo\"\r\n}",
							"options": {
								"raw": {
									"language": "json"
								}
							}
						},
						"url": {
							"raw": "http://localhost:8080/utenti",
							"protocol": "http",
							"host": [
								"localhost"
							],
							"port": "8080",
							"path": [
								"utenti"
							]
						}
					},
					"response": []
				},
				{
					"name": "utenti-del",
					"request": {
						"method": "DELETE",
						"header": [],
						"url": {
							"raw": "http://localhost:8080/utenti/3",
							"protocol": "http",
							"host": [
								"localhost"
							],
							"port": "8080",
							"path": [
								"utenti",
								"3"
							]
						}
					},
					"response": []
				}
			]
		},
		{
			"name": "prenotazioni",
			"item": [
				{
					"name": "prenotazioniList",
					"request": {
						"method": "GET",
						"header": [],
						"url": {
							"raw": "http://localhost:8080/prenotazioni",
							"protocol": "http",
							"host": [
								"localhost"
							],
							"port": "8080",
							"path": [
								"prenotazioni"
							]
						}
					},
					"response": []
				},
				{
					"name": "prenotazioni-byId",
					"request": {
						"method": "GET",
						"header": [],
						"url": {
							"raw": "http://localhost:8080/prenotazioni/1",
							"protocol": "http",
							"host": [
								"localhost"
							],
							"port": "8080",
							"path": [
								"prenotazioni",
								"1"
							]
						}
					},
					"response": []
				},
				{
					"name": "prenotazioni_page",
					"request": {
						"method": "GET",
						"header": [],
						"url": {
							"raw": "http://localhost:8080/prenotazioni_page",
							"protocol": "http",
							"host": [
								"localhost"
							],
							"port": "8080",
							"path": [
								"prenotazioni_page"
							]
						}
					},
					"response": []
				},
				{
					"name": "prenotazioni-put",
					"request": {
						"method": "PUT",
						"header": [],
						"body": {
							"mode": "raw",
							"raw": "{\r\n    \"dataScadenza\": \"2023-02-15\"\r\n}",
							"options": {
								"raw": {
									"language": "json"
								}
							}
						},
						"url": {
							"raw": "http://localhost:8080/prenotazioni/1",
							"protocol": "http",
							"host": [
								"localhost"
							],
							"port": "8080",
							"path": [
								"prenotazioni",
								"1"
							]
						}
					},
					"response": []
				},
				{
					"name": "prenotazioni-post",
					"request": {
						"method": "POST",
						"header": [],
						"body": {
							"mode": "raw",
							"raw": "{\r\n\"dataPrenotazione\": \"2023-02-15\",\r\n    \"dataScadenza\": \"2023-02-16\",\r\n    \"nmaxPartecipanti\": 3\r\n}\r\n",
							"options": {
								"raw": {
									"language": "json"
								}
							}
						},
						"url": {
							"raw": "http://localhost:8080/prenotazioni",
							"protocol": "http",
							"host": [
								"localhost"
							],
							"port": "8080",
							"path": [
								"prenotazioni"
							]
						}
					},
					"response": []
				},
				{
					"name": "prenotazioni-del",
					"request": {
						"method": "DELETE",
						"header": [],
						"url": {
							"raw": "http://localhost:8080/prenotazioni/2",
							"protocol": "http",
							"host": [
								"localhost"
							],
							"port": "8080",
							"path": [
								"prenotazioni",
								"2"
							]
						}
					},
					"response": []
				}
			]
		}
	]
}